.gitignore
.isort.cfg
.pre-commit-config.yaml
LICENSE
README.rst
pyproject.toml
setup.py
certbot_dns_plugins/__init__.py
certbot_dns_plugins/dnspod.py
certbot_dns_plugins.egg-info/PKG-INFO
certbot_dns_plugins.egg-info/SOURCES.txt
certbot_dns_plugins.egg-info/dependency_links.txt
certbot_dns_plugins.egg-info/entry_points.txt
certbot_dns_plugins.egg-info/requires.txt
certbot_dns_plugins.egg-info/top_level.txt